fishsound_finder/__init__.py
fishsound_finder/_version.py
fishsound_finder/detector.py
fishsound_finder-0.1.1.dist-info/LICENSE
fishsound_finder-0.1.1.dist-info/METADATA
fishsound_finder-0.1.1.dist-info/WHEEL
fishsound_finder-0.1.1.dist-info/entry_points.txt
fishsound_finder-0.1.1.dist-info/top_level.txt
fishsound_finder-0.1.1.dist-info/RECORD
