Metadata-Version: 2.1
Name: fishsound-finder
Version: 0.1.1
Summary: Python software to automatically detect fish sounds in passive acoustic recordings
Home-page: https://github.com/xaviermouy/FishSound_Finder
Author: Xavier Mouy
Author-email: xaviermouy@outlook.com
License: BSD license
Keywords: fish sounds
Classifier: Development Status :: 3 - Alpha
Classifier: Intended Audience :: Developers
Classifier: Programming Language :: Python :: 3.9
Classifier: License :: OSI Approved :: BSD License
Classifier: Operating System :: OS Independent
Classifier: Natural Language :: English
Requires-Python: >=3.9.0, <3.10.0
License-File: LICENSE
Requires-Dist: absl-py (==2.1.0)
Requires-Dist: appdirs (==1.4.4)
Requires-Dist: asciitree (==0.3.3)
Requires-Dist: asttokens (==2.4.1)
Requires-Dist: astunparse (==1.6.3)
Requires-Dist: attrs (==24.2.0)
Requires-Dist: audioread (==3.0.1)
Requires-Dist: beautifulsoup4 (==4.12.3)
Requires-Dist: blosc2 (==2.5.1)
Requires-Dist: bokeh (==3.4.3)
Requires-Dist: Bottleneck (==1.4.0)
Requires-Dist: cachetools (==5.4.0)
Requires-Dist: certifi (==2024.7.4)
Requires-Dist: cffi (==1.17.0)
Requires-Dist: cfgv (==3.4.0)
Requires-Dist: cftime (==1.6.4)
Requires-Dist: charset-normalizer (==3.3.2)
Requires-Dist: click (==8.1.7)
Requires-Dist: cloudpickle (==3.0.0)
Requires-Dist: colorama (==0.4.6)
Requires-Dist: comm (==0.2.2)
Requires-Dist: contourpy (==1.2.1)
Requires-Dist: coverage (==7.6.1)
Requires-Dist: cycler (==0.12.1)
Requires-Dist: dask (==2024.8.0)
Requires-Dist: dask-expr (==1.1.10)
Requires-Dist: dask-image (==2024.5.3)
Requires-Dist: datetime-glob (==1.0.8)
Requires-Dist: decorator (==5.1.1)
Requires-Dist: distlib (==0.3.8)
Requires-Dist: distributed (==2024.8.0)
Requires-Dist: docopt (==0.6.2)
Requires-Dist: eccodes (==1.2.0)
Requires-Dist: ecosound (==0.0.25)
Requires-Dist: exceptiongroup (==1.2.2)
Requires-Dist: execnet (==2.1.1)
Requires-Dist: executing (==2.0.1)
Requires-Dist: fasteners (==0.19)
Requires-Dist: filelock (==3.15.4)
Requires-Dist: flatbuffers (==24.3.25)
Requires-Dist: flexcache (==0.3)
Requires-Dist: flexparser (==0.3.1)
Requires-Dist: flox (==0.9.9)
Requires-Dist: fonttools (==4.53.1)
Requires-Dist: fsspec (==2024.6.1)
Requires-Dist: gast (==0.6.0)
Requires-Dist: google-auth (==2.33.0)
Requires-Dist: google-auth-oauthlib (==0.4.6)
Requires-Dist: google-pasta (==0.2.0)
Requires-Dist: grpcio (==1.65.4)
Requires-Dist: h5netcdf (==1.3.0)
Requires-Dist: h5py (==3.11.0)
Requires-Dist: hypothesis (==6.110.1)
Requires-Dist: identify (==2.6.0)
Requires-Dist: idna (==3.7)
Requires-Dist: imageio (==2.34.2)
Requires-Dist: importlib-metadata (==8.2.0)
Requires-Dist: importlib-resources (==6.4.0)
Requires-Dist: iniconfig (==2.0.0)
Requires-Dist: ipympl (==0.9.4)
Requires-Dist: ipython (==8.18.1)
Requires-Dist: ipython-genutils (==0.2.0)
Requires-Dist: ipywidgets (==8.1.3)
Requires-Dist: jedi (==0.19.1)
Requires-Dist: Jinja2 (==3.1.4)
Requires-Dist: joblib (==1.4.2)
Requires-Dist: jupyterlab-widgets (==3.0.11)
Requires-Dist: keras (==2.8.0)
Requires-Dist: Keras-Preprocessing (==1.1.2)
Requires-Dist: ketos (==2.6.2)
Requires-Dist: kiwisolver (==1.4.5)
Requires-Dist: lazy-loader (==0.4)
Requires-Dist: lexery (==1.2.0)
Requires-Dist: libclang (==18.1.1)
Requires-Dist: librosa (==0.10.2.post1)
Requires-Dist: llvmlite (==0.43.0)
Requires-Dist: locket (==1.0.0)
Requires-Dist: lz4 (==4.3.3)
Requires-Dist: Markdown (==3.6)
Requires-Dist: MarkupSafe (==2.1.5)
Requires-Dist: matplotlib (==3.9.1.post1)
Requires-Dist: matplotlib-inline (==0.1.7)
Requires-Dist: msgpack (==1.0.8)
Requires-Dist: mypy (==1.11.1)
Requires-Dist: mypy-extensions (==1.0.0)
Requires-Dist: nc-time-axis (==1.4.1)
Requires-Dist: ndindex (==1.8)
Requires-Dist: netCDF4 (==1.7.1.post1)
Requires-Dist: networkx (==3.2.1)
Requires-Dist: nodeenv (==1.9.1)
Requires-Dist: numba (==0.60.0)
Requires-Dist: numbagg (==0.8.1)
Requires-Dist: numcodecs (==0.12.1)
Requires-Dist: numexpr (==2.10.1)
Requires-Dist: numpy (==1.26.4)
Requires-Dist: numpy-groupies (==0.11.2)
Requires-Dist: oauthlib (==3.2.2)
Requires-Dist: opencv-python (==4.10.0.84)
Requires-Dist: opt-einsum (==3.3.0)
Requires-Dist: packaging (==24.1)
Requires-Dist: pandas (==2.2.2)
Requires-Dist: parso (==0.8.4)
Requires-Dist: partd (==1.4.2)
Requires-Dist: pillow (==10.4.0)
Requires-Dist: PIMS (==0.7)
Requires-Dist: Pint (==0.24.3)
Requires-Dist: platformdirs (==4.2.2)
Requires-Dist: pluggy (==1.5.0)
Requires-Dist: pooch (==1.8.2)
Requires-Dist: pre-commit (==3.8.0)
Requires-Dist: prompt-toolkit (==3.0.47)
Requires-Dist: protobuf (==3.20.3)
Requires-Dist: psutil (==6.0.0)
Requires-Dist: pure-eval (==0.2.3)
Requires-Dist: py-cpuinfo (==9.0.0)
Requires-Dist: pyarrow (==17.0.0)
Requires-Dist: pyarrow-hotfix (==0.6)
Requires-Dist: pyasn1 (==0.6.0)
Requires-Dist: pyasn1-modules (==0.4.0)
Requires-Dist: pycparser (==2.22)
Requires-Dist: pydap (==3.4.1)
Requires-Dist: Pygments (==2.18.0)
Requires-Dist: pyparsing (==3.1.2)
Requires-Dist: pytest (==8.3.2)
Requires-Dist: pytest-cov (==5.0.0)
Requires-Dist: pytest-env (==1.1.3)
Requires-Dist: pytest-timeout (==2.3.1)
Requires-Dist: pytest-xdist (==3.6.1)
Requires-Dist: python-dateutil (==2.9.0.post0)
Requires-Dist: pytz (==2024.1)
Requires-Dist: PyYAML (==6.0.2)
Requires-Dist: requests (==2.32.3)
Requires-Dist: requests-oauthlib (==2.0.0)
Requires-Dist: rsa (==4.9)
Requires-Dist: ruff (==0.5.7)
Requires-Dist: scikit-image (==0.24.0)
Requires-Dist: scikit-learn (==1.5.1)
Requires-Dist: scipy (==1.13.1)
Requires-Dist: seaborn (==0.13.2)
Requires-Dist: silence-tensorflow (==1.2.2)
Requires-Dist: six (==1.16.0)
Requires-Dist: slicerator (==1.1.0)
Requires-Dist: sortedcontainers (==2.4.0)
Requires-Dist: soundfile (==0.12.1)
Requires-Dist: soupsieve (==2.5)
Requires-Dist: soxr (==0.4.0)
Requires-Dist: stack-data (==0.6.3)
Requires-Dist: tables (==3.9.2)
Requires-Dist: tblib (==3.0.0)
Requires-Dist: tensorboard (==2.8.0)
Requires-Dist: tensorboard-data-server (==0.6.1)
Requires-Dist: tensorboard-plugin-wit (==1.8.1)
Requires-Dist: tensorflow (==2.8.0)
Requires-Dist: tensorflow-io-gcs-filesystem (==0.31.0)
Requires-Dist: termcolor (==2.4.0)
Requires-Dist: tf-estimator-nightly (==2.8.0.dev2021122109)
Requires-Dist: threadpoolctl (==3.5.0)
Requires-Dist: tifffile (==2024.7.24)
Requires-Dist: tomli (==2.0.1)
Requires-Dist: toolz (==0.12.1)
Requires-Dist: tornado (==6.4.1)
Requires-Dist: tqdm (==4.66.5)
Requires-Dist: traitlets (==5.14.3)
Requires-Dist: typing-extensions (==4.12.2)
Requires-Dist: tzdata (==2024.1)
Requires-Dist: urllib3 (==2.2.2)
Requires-Dist: version-parser (==1.0.1)
Requires-Dist: virtualenv (==20.26.3)
Requires-Dist: wcwidth (==0.2.13)
Requires-Dist: WebOb (==1.8.7)
Requires-Dist: Werkzeug (==3.0.3)
Requires-Dist: widgetsnbextension (==4.0.11)
Requires-Dist: wrapt (==1.16.0)
Requires-Dist: xarray (==2024.7.0)
Requires-Dist: xyzservices (==2024.6.0)
Requires-Dist: zarr (==2.18.2)
Requires-Dist: zict (==3.0.0)
Requires-Dist: zipp (==3.19.2)
